cldf_rel/__init__.py
cldf_rel-0.1.0.dist-info/LICENSE
cldf_rel-0.1.0.dist-info/METADATA
cldf_rel-0.1.0.dist-info/WHEEL
cldf_rel-0.1.0.dist-info/entry_points.txt
cldf_rel-0.1.0.dist-info/RECORD
